aviewpy/__init__.py
aviewpy/contact.py
aviewpy/cs.py
aviewpy/model.py
aviewpy/move.py
aviewpy/objects.py
aviewpy/results.py
aviewpy/sim.py
aviewpy/variables.py
aviewpy/files/__init__.py
aviewpy/files/acf.py
aviewpy/files/adm.py
aviewpy/files/bin.py
aviewpy/files/cmd.py
aviewpy/files/mac.py
aviewpy/files/msg.py
aviewpy/files/shell.py
aviewpy/files/to.py
aviewpy/ui/__init__.py
aviewpy/ui/alerts.py
aviewpy/ui/messages.py
aviewpy/ui/progressbar.py
aviewpy/ui/turn_on_all_force_graphics.py
aviewpy/ui/windows.py
aviewpy/utils/__init__.py
aviewpy/utils/dereferencer.py
aviewpy/utils/excepthook.py
aviewpy/utils/fbd.py
aviewpy/utils/res_to_csv.py
aviewpy/utils/utils.py
aviewpy-1.3.8.dist-info/LICENSE
aviewpy-1.3.8.dist-info/METADATA
aviewpy-1.3.8.dist-info/WHEEL
aviewpy-1.3.8.dist-info/top_level.txt
aviewpy-1.3.8.dist-info/RECORD
